iplot/__init__.py
iplot-0.0.0.dist-info/METADATA
iplot-0.0.0.dist-info/WHEEL
iplot-0.0.0.dist-info/top_level.txt
iplot-0.0.0.dist-info/RECORD
