Metadata-Version: 1.1
Name: iplot
Version: 0.0.0
Summary: IPlot is a plotting library
Home-page: https://github.com/gyli/iplot
Author: Guangyang Li
Author-email: mail@guangyangli.com
License: GPL
Keywords: iplot
Platform: UNKNOWN
Classifier: Programming Language :: Python :: 3.7
